pythopix/__init__.py
pythopix/augmentations.py
pythopix/comparison.py
pythopix/data_handling.py
pythopix/dataset_evaluation.py
pythopix/file_operations.py
pythopix/labels_operations.py
pythopix/model_operations.py
pythopix/models.py
pythopix/theme.py
pythopix/utils.py
pythopix-0.5.3.dist-info/METADATA
pythopix-0.5.3.dist-info/WHEEL
pythopix-0.5.3.dist-info/top_level.txt
pythopix-0.5.3.dist-info/RECORD
