Metadata-Version: 2.1
Name: pythopix
Version: 0.5.3
Summary: An image dataset evaluation library using YOLO models
Author: Boris
Author-email: borisculjak@gmail.com
Project-URL: Documentation, https://github.com/boriscu/pythopix/blob/main/docs/DOCUMENTATION.md
Project-URL: Source Code, https://github.com/boriscu/pythopix
Requires-Dist: torch
Requires-Dist: tqdm
Requires-Dist: ultralytics
Requires-Dist: rich
Requires-Dist: numpy
Requires-Dist: matplotlib
Requires-Dist: opencv-python
Requires-Dist: pandas
Requires-Dist: seaborn
